hf_mem/__init__.py
hf_mem/cli.py
hf_mem/metadata.py
hf_mem/print.py
hf_mem/py.typed
hf_mem/types.py
hf_mem-0.4.2.dist-info/licenses/LICENSE
hf_mem-0.4.2.dist-info/WHEEL
hf_mem-0.4.2.dist-info/entry_points.txt
hf_mem-0.4.2.dist-info/METADATA
hf_mem-0.4.2.dist-info/RECORD
