Metadata-Version: 2.4
Name: hf-mem
Version: 0.4.2
Summary: A CLI to estimate inference memory requirements for Hugging Face models, written in Python.
Author: Alvaro Bartolome
Author-email: Alvaro Bartolome <alvarobartt@gmail.com>
License-Expression: MIT
License-File: LICENSE
Requires-Dist: httpx[http2]>=0.28.1
Requires-Python: >=3.10
